lcfv/__init__.py
lcfv/core.py
lcfv/fisher.py
lcfv/sift.py
lcfv-0.1.1.dist-info/licenses/LICENSE
lcfv-0.1.1.dist-info/METADATA
lcfv-0.1.1.dist-info/WHEEL
lcfv-0.1.1.dist-info/top_level.txt
lcfv-0.1.1.dist-info/RECORD
